vulkan_object/__init__.py
vulkan_object/apiconventions.py
vulkan_object/base_generator.py
vulkan_object/cgenerator.py
vulkan_object/generator.py
vulkan_object/parse_dependency.py
vulkan_object/reg.py
vulkan_object/stripAPI.py
vulkan_object/video.xml
vulkan_object/vk.xml
vulkan_object/vkconventions.py
vulkan_object/vulkan_object.py
vulkan_object/spec_tools/conventions.py
vulkan_object/spec_tools/util.py
vulkan_object-1.4.342.post2.dist-info/licenses/LICENSE
vulkan_object-1.4.342.post2.dist-info/METADATA
vulkan_object-1.4.342.post2.dist-info/WHEEL
vulkan_object-1.4.342.post2.dist-info/top_level.txt
vulkan_object-1.4.342.post2.dist-info/RECORD
