Metadata-Version: 2.4
Name: vulkan-object
Version: 1.4.342.post2
Summary: An easy-to-use Python wrapper for the Vulkan API registry.
Author-email: Spencer Fricke <spencer@lunarg.com>
Classifier: Programming Language :: Python :: 3
Classifier: Operating System :: OS Independent
Requires-Python: >=3.10
License-File: LICENSE
Dynamic: license-file
